hb_config-0.5.1.dist-info/DESCRIPTION.rst
hb_config-0.5.1.dist-info/METADATA
hb_config-0.5.1.dist-info/RECORD
hb_config-0.5.1.dist-info/WHEEL
hb_config-0.5.1.dist-info/metadata.json
hb_config-0.5.1.dist-info/top_level.txt
hbconfig/__init__.py
