Metadata-Version: 2.0
Name: hb-config
Version: 0.5.1
Summary: easy to configure your python packge
Home-page: https://github.com/DongjunLee/hb-config
Author: Dongjun Lee
Author-email: humanbrain.djlee@gmail.com
License: MIT license
Keywords: config,util
Platform: UNKNOWN
Classifier: Intended Audience :: Developers
Classifier: Programming Language :: Python :: 3.6
Classifier: Topic :: Software Development :: Libraries :: Python Modules
Requires-Dist: pyyaml
